huiqanghui_mllib/__init__.py
huiqanghui_mllib/_nbdev.py
huiqanghui_mllib/huqianghuiNN.py
huiqanghui_mllib-0.0.1.dist-info/LICENSE
huiqanghui_mllib-0.0.1.dist-info/METADATA
huiqanghui_mllib-0.0.1.dist-info/WHEEL
huiqanghui_mllib-0.0.1.dist-info/entry_points.txt
huiqanghui_mllib-0.0.1.dist-info/top_level.txt
huiqanghui_mllib-0.0.1.dist-info/RECORD
