Metadata-Version: 2.1
Name: huiqanghui-mllib
Version: 0.0.1
Summary: huqianghui ml learn libs
Home-page: https://github.com/huqianghui/huiqanghui_mllib
Author: huqianghui
Author-email: huqianghui0613@163.com
License: Apache Software License 2.0
Keywords: machine learning
Platform: UNKNOWN
Classifier: Development Status :: 3 - Alpha
Classifier: Intended Audience :: Developers
Classifier: License :: OSI Approved :: Apache Software License
Classifier: Natural Language :: English
Classifier: Programming Language :: Python :: 3.6
Classifier: Programming Language :: Python :: 3.7
Classifier: Programming Language :: Python :: 3.8
Requires-Python: >=3.6
Requires-Dist: nbformat (>=4.4.0)
Requires-Dist: nbconvert (>=5.6.1)
